audiofile/__init__.py
audiofile/core/__init__.py
audiofile/core/conftest.py
audiofile/core/convert.py
audiofile/core/info.py
audiofile/core/io.py
audiofile/core/utils.py
docs/benchmark.rst
docs/changelog.rst
docs/conf.py
docs/contributing.rst
docs/index.rst
docs/installation.rst
docs/requirements.txt
docs/usage.rst
docs/_templates/autosummary/base.rst
docs/_templates/autosummary/class.rst
docs/_templates/autosummary/function.rst
docs/api-src/audiofile.rst
docs/benchmark/README.md
docs/benchmark/benchmark_info.py
docs/benchmark/benchmark_read.py
docs/benchmark/generate_audio.sh
docs/benchmark/install_dependencies.sh
docs/benchmark/loaders.py
docs/benchmark/plot.py
docs/benchmark/requirements.txt
docs/benchmark/requirements.txt.lock
docs/benchmark/run.sh
docs/benchmark/utils.py
docs/benchmark/results/benchmark_info_flac.pickle
docs/benchmark/results/benchmark_info_mp3.pickle
docs/benchmark/results/benchmark_info_mp4.pickle
docs/benchmark/results/benchmark_info_ogg.pickle
docs/benchmark/results/benchmark_info_wav.pickle
docs/benchmark/results/benchmark_mp4_info.png
docs/benchmark/results/benchmark_read_flac.pickle
docs/benchmark/results/benchmark_read_mp3.pickle
docs/benchmark/results/benchmark_read_mp4.pickle
docs/benchmark/results/benchmark_read_ogg.pickle
docs/benchmark/results/benchmark_read_wav.pickle
docs/benchmark/results/benchmark_wav-flac-ogg-mp3-mp4_read.png
docs/benchmark/results/benchmark_wav-flac-ogg-mp3_info.png
tests/requirements.txt
tests/test_audiofile.py
tests/assets/README.md
tests/assets/gs-16b-1c-44100hz.aac
tests/assets/gs-16b-1c-44100hz.m4a
tests/assets/gs-16b-1c-44100hz.opus
tests/assets/gs-16b-1c-8000hz.amr
tests/assets/video.mp4
audiofile-1.5.0.dist-info/LICENSE
audiofile-1.5.0.dist-info/METADATA
audiofile-1.5.0.dist-info/WHEEL
audiofile-1.5.0.dist-info/top_level.txt
audiofile-1.5.0.dist-info/RECORD
