Metadata-Version: 2.1
Name: audiofile
Version: 1.5.0
Summary: Fast reading of all kind of audio files
Author-email: Hagen Wierstorf <hwierstorf@audeering.com>, Johannes Wagner <jwagner@audeering.com>, Christian Geng <cgeng@audeering.com>
License: MIT License
Project-URL: repository, https://github.com/audeering/audiofile/
Project-URL: documentation, https://audeering.github.io/audiofile/
Keywords: audio,tools
Classifier: Development Status :: 5 - Production/Stable
Classifier: Intended Audience :: Science/Research
Classifier: Intended Audience :: Developers
Classifier: License :: OSI Approved :: MIT License
Classifier: Operating System :: OS Independent
Classifier: Programming Language :: Python
Classifier: Programming Language :: Python :: 3
Classifier: Programming Language :: Python :: 3.8
Classifier: Programming Language :: Python :: 3.9
Classifier: Programming Language :: Python :: 3.10
Classifier: Programming Language :: Python :: 3.11
Classifier: Programming Language :: Python :: 3.12
Classifier: Topic :: Scientific/Engineering
Classifier: Topic :: Multimedia :: Sound/Audio
License-File: LICENSE
Requires-Dist: audeer
Requires-Dist: audmath>=1.3.0
Requires-Dist: numpy
Requires-Dist: soundfile>=0.12.1
